perplexity_mcp/__init__.py
perplexity_mcp/server.py
perplexity_mcp-0.1.7.dist-info/METADATA
perplexity_mcp-0.1.7.dist-info/WHEEL
perplexity_mcp-0.1.7.dist-info/entry_points.txt
perplexity_mcp-0.1.7.dist-info/licenses/LICENSE
perplexity_mcp-0.1.7.dist-info/RECORD
