Metadata-Version: 2.4
Name: perplexity-mcp
Version: 0.1.7
Summary: MCP integration for Perplexity AI web searches
Author: Jason Allen
License-File: LICENSE
Requires-Python: >=3.11
Requires-Dist: aiohttp>=3.8.0
Requires-Dist: mcp>=1.0.2
Requires-Dist: pydantic>=2.0.0
